AUTHORS.rst
CONTRIBUTING.rst
HISTORY.rst
LICENSE
MANIFEST.in
README.rst
setup.py
probe/__init__.py
probe/cli.py
probe/config.py
probe/errors.py
probe/outputs.py
probe/questions.py
probe.egg-info/PKG-INFO
probe.egg-info/SOURCES.txt
probe.egg-info/dependency_links.txt
probe.egg-info/entry_points.txt
probe.egg-info/not-zip-safe
probe.egg-info/requires.txt
probe.egg-info/top_level.txt