Metadata-Version: 1.1
Name: probe
Version: 0.0.2
Summary: Probe lets you ship personal metrics (feelings, energy level, productivity) to external services for analysis.
Home-page: https://github.com/BrianHicks/probe
Author: Brian Hicks
Author-email: brian@brianthicks.com
License: BSD
Keywords: probe
Platform: UNKNOWN
Classifier: Development Status :: 2 - Pre-Alpha
Classifier: Intended Audience :: Developers
Classifier: License :: OSI Approved :: BSD License
Classifier: Natural Language :: English
Classifier: Programming Language :: Python :: 2
Classifier: Programming Language :: Python :: 2.7
Classifier: Programming Language :: Python :: 3
Classifier: Programming Language :: Python :: 3.3
